wandb_summarizer/__init__.py
wandb_summarizer/download.py
wandb_summarizer/download_test.py
wandb_summarizer/export.py
wandb_summarizer/export_test.py
wandb_summarizer-0.1.2.dist-info/LICENSE.md
wandb_summarizer-0.1.2.dist-info/METADATA
wandb_summarizer-0.1.2.dist-info/WHEEL
wandb_summarizer-0.1.2.dist-info/entry_points.txt
wandb_summarizer-0.1.2.dist-info/top_level.txt
wandb_summarizer-0.1.2.dist-info/RECORD
