Metadata-Version: 2.1
Name: wandb-summarizer
Version: 0.1.2
Summary: A tiny CSV export micro-library for Weights and Biases.
Home-page: https://github.com/sampottinger/wandb_summarizer
Author: A. Samuel Pottinger
License: MIT
Download-URL: https://github.com/sampottinger/wandb_summarizer/archive/master.zip
Platform: UNKNOWN
Classifier: Development Status :: 4 - Beta
Classifier: Intended Audience :: Developers
Classifier: Intended Audience :: Financial and Insurance Industry
Classifier: Intended Audience :: Information Technology
Classifier: Intended Audience :: Legal Industry
Classifier: Intended Audience :: Science/Research
Classifier: Intended Audience :: Healthcare Industry
Classifier: Intended Audience :: Telecommunications Industry
Classifier: License :: OSI Approved :: MIT License
Classifier: Natural Language :: English
Classifier: Operating System :: OS Independent
Classifier: Topic :: Scientific/Engineering :: Artificial Intelligence
Classifier: Topic :: Scientific/Engineering :: Information Analysis
Classifier: Topic :: Text Processing
Requires-Dist: wandb
